officetimer/__init__.py
officetimer/timer_controller.py
officetimer-0.2.1.dist-info/LICENSE.txt
officetimer-0.2.1.dist-info/METADATA
officetimer-0.2.1.dist-info/WHEEL
officetimer-0.2.1.dist-info/entry_points.txt
officetimer-0.2.1.dist-info/top_level.txt
officetimer-0.2.1.dist-info/RECORD
