Metadata-Version: 2.1
Name: officetimer
Version: 0.2.1
Summary: Office Timer - Manage work life balance
Home-page: https://github.com/adityakamble49/office-timer
Author: adityakamble49
Author-email: adityakamble49@gmail.com
License: Apache-2.0
Platform: UNKNOWN
